augmentedtree/__init__.py
augmentedtree/abstractbaseclasses.py
augmentedtree/augmentation.py
augmentedtree/core.py
augmentedtree/tree.py
augmentedtree/treeitems.py
augmentedtree/treeitemselection.py
augmentedtree-0.2a0.dist-info/LICENSE
augmentedtree-0.2a0.dist-info/METADATA
augmentedtree-0.2a0.dist-info/WHEEL
augmentedtree-0.2a0.dist-info/top_level.txt
augmentedtree-0.2a0.dist-info/RECORD
