Metadata-Version: 2.1
Name: augmentedtree
Version: 0.2a0
Summary: Easy navigation within nested data of mappings (dict, ...) and sequences (list, ...). Easy access of values via single keys within these nested data structures. Enables different (human readable) representation of nested data structures.
Home-page: https://gitlab.com/david.scheliga/augmentedtree
Author: David Scheliga
Author-email: david.scheliga@ivw.uni-kl.de
License: GNU General Public License v3 (GPLv3)
Project-URL: Documentation, https://augmentedtree.readthedocs.io/en/latest/
Project-URL: Source Code Repository, https://gitlab.com/david.scheliga/augmentedtree
Keywords: dictionary,mapping,list,sequence,nested,handling,navigation,selection
Platform: UNKNOWN
Classifier: Development Status :: 3 - Alpha
Classifier: License :: OSI Approved :: GNU General Public License v3 or later (GPLv3+)
Classifier: Operating System :: OS Independent
Classifier: Programming Language :: Python :: 3
Requires-Python: >=3.6
Requires-Dist: pandas
Requires-Dist: numpy
